schematics/__init__.py
schematics/common.py
schematics/compat.py
schematics/datastructures.py
schematics/exceptions.py
schematics/models.py
schematics/transforms.py
schematics/util.py
schematics/validate.py
schematics/contrib/__init__.py
schematics/contrib/mongo.py
schematics/types/__init__.py
schematics/types/base.py
schematics/types/compound.py
schematics/types/serializable.py
schematics/types/temporal.py
schematics_patched-1.1.2.dist-info/LICENSE.txt
schematics_patched-1.1.2.dist-info/METADATA
schematics_patched-1.1.2.dist-info/RECORD
schematics_patched-1.1.2.dist-info/WHEEL
schematics_patched-1.1.2.dist-info/top_level.txt
