Metadata-Version: 2.1
Name: schematics-patched
Version: 1.1.2
Summary: A aptched version of schematics 1.1.1 that can pickle with multiprocessing
Home-page: http://github.com/pombredanne/schematics
Author: James Dennis, Jökull Sólberg, Jóhann Þorvaldur Bergþórsson
Author-email: jdennis@gmail.com, jokull@plainvanillagames.com, johann@plainvanillagames.com
License: BSD
Platform: UNKNOWN
Classifier: Environment :: Other Environment
Classifier: Intended Audience :: Developers
Classifier: License :: Other/Proprietary License
Classifier: Operating System :: POSIX
Classifier: Programming Language :: Python
Classifier: Programming Language :: Python :: 2.6
Classifier: Programming Language :: Python :: 2.7
Classifier: Programming Language :: Python :: 3
Classifier: Programming Language :: Python :: 3.3
Classifier: Programming Language :: Python :: 3.4
Requires-Dist: six (>=1.7.3)
